jpg2pdf.py
jpg2pdf-0.1.0.dist-info/LICENSE
jpg2pdf-0.1.0.dist-info/METADATA
jpg2pdf-0.1.0.dist-info/WHEEL
jpg2pdf-0.1.0.dist-info/top_level.txt
jpg2pdf-0.1.0.dist-info/RECORD
