Metadata-Version: 2.1
Name: jpg2pdf
Version: 0.1.0
Summary: Python module for generating PDF document from JPEG files.
Home-page: https://github.com/leejeonghun/jpg2pdf
Author: Jeonghun Lee
License: BSD
Platform: any
Requires-Python: >=3.6
